{
  "parent": "minecraft:recipes/root",
  "criteria": {
    "has_endstone_alexandrite_ore": {
      "conditions": {
        "items": [
          {
            "items": [
              "nordmod:endstone_alexandrite_ore"
            ]
          }
        ]
      },
      "trigger": "minecraft:inventory_changed"
    },
    "has_the_recipe": {
      "conditions": {
        "recipe": "nordmod:alexandrite_smelting_endstone_alexandrite_ore"
      },
      "trigger": "minecraft:recipe_unlocked"
    }
  },
  "requirements": [
    [
      "has_endstone_alexandrite_ore",
      "has_the_recipe"
    ]
  ],
  "rewards": {
    "recipes": [
      "nordmod:alexandrite_smelting_endstone_alexandrite_ore"
    ]
  },
  "sends_telemetry_event": false
}